{
  "project_info": {
    "project_number": "1038917248918",
    "firebase_url": "https://datastructures-register.firebaseio.com",
    "project_id": "datastructures-register",
    "storage_bucket": "datastructures-register.appspot.com"
  },
  "client": [
    {
      "client_info": {
        "mobilesdk_app_id": "1:1038917248918:android:74953f323a8448c4",
        "android_client_info": {
          "package_name": "edu.gsu.ds_register"
        }
      },
      "oauth_client": [
        {
          "client_id": "1038917248918-i6atfl51tnb7avkt0m2oc2gh5m8nr3q1.apps.googleusercontent.com",
          "client_type": 1,
          "android_info": {
            "package_name": "edu.gsu.ds_register",
            "certificate_hash": "BEB8EE7DE79650E4671A2E22FFBD7588A1BF8DD3"
          }
        },
        {
          "client_id": "1038917248918-ciidfcsgjpqboul4tomtqb60gf69ir0e.apps.googleusercontent.com",
          "client_type": 3
        }
      ],
      "api_key": [
        {
          "current_key": "AIzaSyAfL9pL9n9ZeVzgD-a4NgFV689IsVkKEB4"
        }
      ],
      "services": {
        "analytics_service": {
          "status": 1
        },
        "appinvite_service": {
          "status": 2,
          "other_platform_oauth_client": [
            {
              "client_id": "1038917248918-ciidfcsgjpqboul4tomtqb60gf69ir0e.apps.googleusercontent.com",
              "client_type": 3
            }
          ]
        },
        "ads_service": {
          "status": 2
        }
      }
    }
  ],
  "configuration_version": "1"
}